falconz/__init__.py
falconz/constants.py
falconz/display.py
falconz/download.py
falconz/falconz.py
falconz/file_utilities.py
falconz/image_conversion.py
falconz/image_processing.py
falconz/input_validation.py
falconz/resources.py
falconz-2.2.1.dist-info/licenses/LICENSE
falconz-2.2.1.dist-info/METADATA
falconz-2.2.1.dist-info/WHEEL
falconz-2.2.1.dist-info/entry_points.txt
falconz-2.2.1.dist-info/top_level.txt
falconz-2.2.1.dist-info/RECORD
