Metadata-Version: 2.4
Name: falconz
Version: 2.2.1
Summary: FalconZ: A streamlined Python package for PET motion correction.
Home-page: https://github.com/QIMP-Team/FALCON
Author: Lalith Kumar Shiyam Sundar
Author-email: Lalith.shiyamsundar@meduniwien.ac.at
License: GPLv3
Keywords: PET motion correction,diffeomorphic imaging,image processing
Classifier: Development Status :: 4 - Beta
Classifier: Intended Audience :: Developers
Classifier: Intended Audience :: Healthcare Industry
Classifier: License :: OSI Approved :: GNU General Public License v3 (GPLv3)
Classifier: Programming Language :: Python :: 3 :: Only
Classifier: Programming Language :: Python :: 3.8
Classifier: Programming Language :: Python :: 3.9
Classifier: Programming Language :: Python :: 3.10
Classifier: Topic :: Scientific/Engineering :: Medical Science Apps.
Requires-Python: >=3.10
License-File: LICENSE
Requires-Dist: nibabel~=3.2.2
Requires-Dist: halo~=0.0.31
Requires-Dist: SimpleITK
Requires-Dist: pydicom~=2.2.2
Requires-Dist: argparse~=1.4.0
Requires-Dist: numpy~=1.25.2
Requires-Dist: mpire~=2.3.3
Requires-Dist: openpyxl~=3.0.9
Requires-Dist: matplotlib
Requires-Dist: pyfiglet~=0.8.post1
Requires-Dist: natsort~=8.1.0
Requires-Dist: pillow>=9.2.0
Requires-Dist: colorama~=0.4.6
Requires-Dist: rich
Requires-Dist: pandas
Requires-Dist: dicom2nifti~=2.4.8
Requires-Dist: requests
Requires-Dist: emoji
Requires-Dist: psutil
Requires-Dist: nilearn
Requires-Dist: scikit-image
Requires-Dist: dask
Requires-Dist: dask[distributed]
Dynamic: author
Dynamic: author-email
Dynamic: classifier
Dynamic: description
Dynamic: home-page
Dynamic: keywords
Dynamic: license
Dynamic: license-file
Dynamic: requires-dist
Dynamic: requires-python
Dynamic: summary
